HQ_Test_Data/__init__.py
HQ_Test_Data/main.py
HQ_Test_Data-0.0.5.dist-info/LICENSE
HQ_Test_Data-0.0.5.dist-info/METADATA
HQ_Test_Data-0.0.5.dist-info/WHEEL
HQ_Test_Data-0.0.5.dist-info/top_level.txt
HQ_Test_Data-0.0.5.dist-info/RECORD
