Metadata-Version: 2.1
Name: HQ-Test-Data
Version: 0.0.5
Summary: A Python package to fetch and print data.
Author-email: Hossam Ibrahim <hossam.ibrahim@hlag.com>
License: Copyright (c) [2023] [Hossam_Ibrahim]
License-File: LICENSE
Requires-Dist: requests
Requires-Dist: pandas
